{
    "name": {
        "translate": "mineeemotes.emote.name.miemfnfstarveddown2",
        "fallback": "Starved ยง4DOWN2 ยงc(FNF)"
    },
    "author": "MineEmotes",
    "description": {
        "translate": "mineeemotes.emote.description.miemfnfstarveddown2",
        "fallback": "Down2"
    },
    "emote": {
        "isLoop": "true",
        "returnTick": 1,
        "beginTick": 0,
        "endTick": 60,
        "stopTick": 61,
        "degrees": false,
        "moves": [
            {
                "tick": 1,
                "easing": "EASEINOUTQUAD",
                "turn": 0,
                "head": {
                    "y": -0.0
                }
            },
            {
                "tick": 5,
                "easing": "EASEINOUTQUAD",
                "turn": 0,
                "head": {
                    "y": -0.0
                }
            },
            {
                "tick": 40,
                "easing": "EASEINOUTQUAD",
                "turn": 0,
                "head": {
                    "y": -0.0
                }
            },
            {
                "tick": 60,
                "easing": "EASEINOUTQUAD",
                "turn": 0,
                "head": {
                    "y": -0.0
                }
            },
            {
                "tick": 1,
                "easing": "EASEINOUTQUAD",
                "turn": 0,
                "head": {
                    "z": -0.0
                }
            },
            {
                "tick": 5,
                "easing": "EASEINOUTQUAD",
                "turn": 0,
                "head": {
                    "z": -0.0
                }
            },
            {
                "tick": 40,
                "easing": "EASEINOUTQUAD",
                "turn": 0,
                "head": {
                    "z": -0.0
                }
            },
            {
                "tick": 60,
                "easing": "EASEINOUTQUAD",
                "turn": 0,
                "head": {
                    "z": -0.0
                }
            },
            {
                "tick": 1,
                "easing": "EASEINOUTQUAD",
                "turn": 0,
                "head": {
                    "x": -0.0
                }
            },
            {
                "tick": 5,
                "easing": "EASEINOUTQUAD",
                "turn": 0,
                "head": {
                    "x": -0.0
                }
            },
            {
                "tick": 40,
                "easing": "EASEINOUTQUAD",
                "turn": 0,
                "head": {
                    "x": -0.0
                }
            },
            {
                "tick": 60,
                "easing": "EASEINOUTQUAD",
                "turn": 0,
                "head": {
                    "x": -0.0
                }
            },
            {
                "tick": 1,
                "easing": "EASEINOUTQUAD",
                "turn": 0,
                "head": {
                    "yaw": -0.0391119047999382
                }
            },
            {
                "tick": 5,
                "easing": "EASEINOUTQUAD",
                "turn": 0,
                "head": {
                    "yaw": -0.0391119010746479
                }
            },
            {
                "tick": 40,
                "easing": "EASEINOUTQUAD",
                "turn": 0,
                "head": {
                    "yaw": -0.0
                }
            },
            {
                "tick": 60,
                "easing": "EASEINOUTQUAD",
                "turn": 0,
                "head": {
                    "yaw": -0.0
                }
            },
            {
                "tick": 1,
                "easing": "EASEINOUTQUAD",
                "turn": 0,
                "head": {
                    "roll": 0.34365609288215637
                }
            },
            {
                "tick": 5,
                "easing": "EASEINOUTQUAD",
                "turn": 0,
                "head": {
                    "roll": 0.3748929798603058
                }
            },
            {
                "tick": 40,
                "easing": "EASEINOUTQUAD",
                "turn": 0,
                "head": {
                    "roll": 0.3383750915527344
                }
            },
            {
                "tick": 60,
                "easing": "EASEINOUTQUAD",
                "turn": 0,
                "head": {
                    "roll": 0.3383750915527344
                }
            },
            {
                "tick": 1,
                "easing": "EASEINOUTQUAD",
                "turn": 0,
                "head": {
                    "pitch": -0.012036537751555443
                }
            },
            {
                "tick": 5,
                "easing": "EASEINOUTQUAD",
                "turn": 0,
                "head": {
                    "pitch": -0.012036537751555443
                }
            },
            {
                "tick": 40,
                "easing": "EASEINOUTQUAD",
                "turn": 0,
                "head": {
                    "pitch": -0.0
                }
            },
            {
                "tick": 60,
                "easing": "EASEINOUTQUAD",
                "turn": 0,
                "head": {
                    "pitch": -0.0
                }
            },
            {
                "tick": 1,
                "easing": "EASEINOUTQUAD",
                "turn": 0,
                "torso": {
                    "yaw": 0.0
                }
            },
            {
                "tick": 5,
                "easing": "EASEINOUTQUAD",
                "turn": 0,
                "torso": {
                    "yaw": 0.0
                }
            },
            {
                "tick": 40,
                "easing": "EASEINOUTQUAD",
                "turn": 0,
                "torso": {
                    "yaw": 0.0
                }
            },
            {
                "tick": 60,
                "easing": "EASEINOUTQUAD",
                "turn": 0,
                "torso": {
                    "yaw": 0.0
                }
            },
            {
                "tick": 1,
                "easing": "EASEINOUTQUAD",
                "turn": 0,
                "torso": {
                    "roll": -0.278130441904068
                }
            },
            {
                "tick": 5,
                "easing": "EASEINOUTQUAD",
                "turn": 0,
                "torso": {
                    "roll": -0.278130441904068
                }
            },
            {
                "tick": 40,
                "easing": "EASEINOUTQUAD",
                "turn": 0,
                "torso": {
                    "roll": -0.278130441904068
                }
            },
            {
                "tick": 60,
                "easing": "EASEINOUTQUAD",
                "turn": 0,
                "torso": {
                    "roll": -0.278130441904068
                }
            },
            {
                "tick": 1,
                "easing": "EASEINOUTQUAD",
                "turn": 0,
                "torso": {
                    "pitch": -0.0
                }
            },
            {
                "tick": 5,
                "easing": "EASEINOUTQUAD",
                "turn": 0,
                "torso": {
                    "pitch": -0.0
                }
            },
            {
                "tick": 40,
                "easing": "EASEINOUTQUAD",
                "turn": 0,
                "torso": {
                    "pitch": -0.0
                }
            },
            {
                "tick": 60,
                "easing": "EASEINOUTQUAD",
                "turn": 0,
                "torso": {
                    "pitch": -0.0
                }
            },
            {
                "tick": 1,
                "easing": "EASEINOUTQUAD",
                "turn": 0,
                "torso": {
                    "y": -0.16731320321559906
                }
            },
            {
                "tick": 5,
                "easing": "EASEINOUTQUAD",
                "turn": 0,
                "torso": {
                    "y": -0.20712822675704956
                }
            },
            {
                "tick": 40,
                "easing": "EASEINOUTQUAD",
                "turn": 0,
                "torso": {
                    "y": -0.16731320321559906
                }
            },
            {
                "tick": 60,
                "easing": "EASEINOUTQUAD",
                "turn": 0,
                "torso": {
                    "y": -0.16731320321559906
                }
            },
            {
                "tick": 1,
                "easing": "EASEINOUTQUAD",
                "turn": 0,
                "torso": {
                    "x": 0.0
                }
            },
            {
                "tick": 5,
                "easing": "EASEINOUTQUAD",
                "turn": 0,
                "torso": {
                    "x": 0.0
                }
            },
            {
                "tick": 40,
                "easing": "EASEINOUTQUAD",
                "turn": 0,
                "torso": {
                    "x": 0.0
                }
            },
            {
                "tick": 60,
                "easing": "EASEINOUTQUAD",
                "turn": 0,
                "torso": {
                    "x": 0.0
                }
            },
            {
                "tick": 1,
                "easing": "EASEINOUTQUAD",
                "turn": 0,
                "torso": {
                    "z": -0.0
                }
            },
            {
                "tick": 5,
                "easing": "EASEINOUTQUAD",
                "turn": 0,
                "torso": {
                    "z": -0.0
                }
            },
            {
                "tick": 40,
                "easing": "EASEINOUTQUAD",
                "turn": 0,
                "torso": {
                    "z": -0.0
                }
            },
            {
                "tick": 60,
                "easing": "EASEINOUTQUAD",
                "turn": 0,
                "torso": {
                    "z": -0.0
                }
            },
            {
                "tick": 1,
                "easing": "EASEINOUTQUAD",
                "turn": 0,
                "rightArm": {
                    "yaw": 1.1160845756530762
                }
            },
            {
                "tick": 5,
                "easing": "EASEINOUTQUAD",
                "turn": 0,
                "rightArm": {
                    "yaw": 1.1160845756530762
                }
            },
            {
                "tick": 40,
                "easing": "EASEINOUTQUAD",
                "turn": 0,
                "rightArm": {
                    "yaw": 1.1160845756530762
                }
            },
            {
                "tick": 60,
                "easing": "EASEINOUTQUAD",
                "turn": 0,
                "rightArm": {
                    "yaw": 1.1160845756530762
                }
            },
            {
                "tick": 1,
                "easing": "EASEINOUTQUAD",
                "turn": 0,
                "rightArm": {
                    "roll": 2.6058807373046875
                }
            },
            {
                "tick": 5,
                "easing": "EASEINOUTQUAD",
                "turn": 0,
                "rightArm": {
                    "roll": 2.9332449436187744
                }
            },
            {
                "tick": 40,
                "easing": "EASEINOUTQUAD",
                "turn": 0,
                "rightArm": {
                    "roll": 2.6058807373046875
                }
            },
            {
                "tick": 60,
                "easing": "EASEINOUTQUAD",
                "turn": 0,
                "rightArm": {
                    "roll": 2.6058807373046875
                }
            },
            {
                "tick": 1,
                "easing": "EASEINOUTQUAD",
                "turn": 0,
                "rightArm": {
                    "y": 3.3015575408935547
                }
            },
            {
                "tick": 5,
                "easing": "EASEINOUTQUAD",
                "turn": 0,
                "rightArm": {
                    "y": 2.7930736541748047
                }
            },
            {
                "tick": 40,
                "easing": "EASEINOUTQUAD",
                "turn": 0,
                "rightArm": {
                    "y": 3.365694999694824
                }
            },
            {
                "tick": 60,
                "easing": "EASEINOUTQUAD",
                "turn": 0,
                "rightArm": {
                    "y": 3.365694999694824
                }
            },
            {
                "tick": 1,
                "easing": "EASEINOUTQUAD",
                "turn": 0,
                "rightArm": {
                    "z": 1.3859752416610718
                }
            },
            {
                "tick": 5,
                "easing": "EASEINOUTQUAD",
                "turn": 0,
                "rightArm": {
                    "z": 1.3859752416610718
                }
            },
            {
                "tick": 40,
                "easing": "EASEINOUTQUAD",
                "turn": 0,
                "rightArm": {
                    "z": 1.3859752416610718
                }
            },
            {
                "tick": 60,
                "easing": "EASEINOUTQUAD",
                "turn": 0,
                "rightArm": {
                    "z": 1.3859752416610718
                }
            },
            {
                "tick": 1,
                "easing": "EASEINOUTQUAD",
                "turn": 0,
                "rightArm": {
                    "x": -4.981686592102051
                }
            },
            {
                "tick": 5,
                "easing": "EASEINOUTQUAD",
                "turn": 0,
                "rightArm": {
                    "x": -4.836498737335205
                }
            },
            {
                "tick": 40,
                "easing": "EASEINOUTQUAD",
                "turn": 0,
                "rightArm": {
                    "x": -5.0
                }
            },
            {
                "tick": 60,
                "easing": "EASEINOUTQUAD",
                "turn": 0,
                "rightArm": {
                    "x": -5.0
                }
            },
            {
                "tick": 1,
                "easing": "EASEINOUTQUAD",
                "turn": 0,
                "rightArm": {
                    "pitch": 1.695583462715149
                }
            },
            {
                "tick": 5,
                "easing": "EASEINOUTQUAD",
                "turn": 0,
                "rightArm": {
                    "pitch": 1.695583462715149
                }
            },
            {
                "tick": 40,
                "easing": "EASEINOUTQUAD",
                "turn": 0,
                "rightArm": {
                    "pitch": 1.695583462715149
                }
            },
            {
                "tick": 60,
                "easing": "EASEINOUTQUAD",
                "turn": 0,
                "rightArm": {
                    "pitch": 1.695583462715149
                }
            },
            {
                "tick": 1,
                "easing": "EASEINOUTQUAD",
                "turn": 0,
                "rightArm": {
                    "bend": -0.02208125591278076
                }
            },
            {
                "tick": 5,
                "easing": "EASEINOUTQUAD",
                "turn": 0,
                "rightArm": {
                    "bend": -0.305472195148468
                }
            },
            {
                "tick": 40,
                "easing": "EASEINOUTQUAD",
                "turn": 0,
                "rightArm": {
                    "bend": -0.005495255813002586
                }
            },
            {
                "tick": 60,
                "easing": "EASEINOUTQUAD",
                "turn": 0,
                "rightArm": {
                    "bend": -0.005495255813002586
                }
            },
            {
                "tick": 1,
                "easing": "EASEINOUTQUAD",
                "turn": 0,
                "leftArm": {
                    "roll": 2.631636619567871
                }
            },
            {
                "tick": 5,
                "easing": "EASEINOUTQUAD",
                "turn": 0,
                "leftArm": {
                    "roll": 2.956073045730591
                }
            },
            {
                "tick": 40,
                "easing": "EASEINOUTQUAD",
                "turn": 0,
                "leftArm": {
                    "roll": 2.589717388153076
                }
            },
            {
                "tick": 60,
                "easing": "EASEINOUTQUAD",
                "turn": 0,
                "leftArm": {
                    "roll": 2.589717388153076
                }
            },
            {
                "tick": 1,
                "easing": "EASEINOUTQUAD",
                "turn": 0,
                "leftArm": {
                    "yaw": 3.1120071411132812
                }
            },
            {
                "tick": 5,
                "easing": "EASEINOUTQUAD",
                "turn": 0,
                "leftArm": {
                    "yaw": 3.0309739112854004
                }
            },
            {
                "tick": 40,
                "easing": "EASEINOUTQUAD",
                "turn": 0,
                "leftArm": {
                    "yaw": 3.1134283542633057
                }
            },
            {
                "tick": 60,
                "easing": "EASEINOUTQUAD",
                "turn": 0,
                "leftArm": {
                    "yaw": 3.1134283542633057
                }
            },
            {
                "tick": 1,
                "easing": "EASEINOUTQUAD",
                "turn": 0,
                "leftArm": {
                    "pitch": 2.0228161811828613
                }
            },
            {
                "tick": 5,
                "easing": "EASEINOUTQUAD",
                "turn": 0,
                "leftArm": {
                    "pitch": 1.9257256984710693
                }
            },
            {
                "tick": 40,
                "easing": "EASEINOUTQUAD",
                "turn": 0,
                "leftArm": {
                    "pitch": 2.027412176132202
                }
            },
            {
                "tick": 60,
                "easing": "EASEINOUTQUAD",
                "turn": 0,
                "leftArm": {
                    "pitch": 2.027412176132202
                }
            },
            {
                "tick": 1,
                "easing": "EASEINOUTQUAD",
                "turn": 0,
                "leftArm": {
                    "y": 2.0
                }
            },
            {
                "tick": 5,
                "easing": "EASEINOUTQUAD",
                "turn": 0,
                "leftArm": {
                    "y": 2.0
                }
            },
            {
                "tick": 40,
                "easing": "EASEINOUTQUAD",
                "turn": 0,
                "leftArm": {
                    "y": 2.0
                }
            },
            {
                "tick": 60,
                "easing": "EASEINOUTQUAD",
                "turn": 0,
                "leftArm": {
                    "y": 2.0
                }
            },
            {
                "tick": 1,
                "easing": "EASEINOUTQUAD",
                "turn": 0,
                "leftArm": {
                    "z": 0.7267565727233887
                }
            },
            {
                "tick": 5,
                "easing": "EASEINOUTQUAD",
                "turn": 0,
                "leftArm": {
                    "z": 0.7267565727233887
                }
            },
            {
                "tick": 40,
                "easing": "EASEINOUTQUAD",
                "turn": 0,
                "leftArm": {
                    "z": 0.7267565727233887
                }
            },
            {
                "tick": 60,
                "easing": "EASEINOUTQUAD",
                "turn": 0,
                "leftArm": {
                    "z": 0.7267565727233887
                }
            },
            {
                "tick": 1,
                "easing": "EASEINOUTQUAD",
                "turn": 0,
                "leftArm": {
                    "x": 5.0
                }
            },
            {
                "tick": 5,
                "easing": "EASEINOUTQUAD",
                "turn": 0,
                "leftArm": {
                    "x": 5.0
                }
            },
            {
                "tick": 40,
                "easing": "EASEINOUTQUAD",
                "turn": 0,
                "leftArm": {
                    "x": 5.0
                }
            },
            {
                "tick": 60,
                "easing": "EASEINOUTQUAD",
                "turn": 0,
                "leftArm": {
                    "x": 5.0
                }
            },
            {
                "tick": 1,
                "easing": "EASEINOUTQUAD",
                "turn": 0,
                "leftArm": {
                    "bend": -0.17397020757198334
                }
            },
            {
                "tick": 5,
                "easing": "EASEINOUTQUAD",
                "turn": 0,
                "leftArm": {
                    "bend": -0.12700115144252777
                }
            },
            {
                "tick": 40,
                "easing": "EASEINOUTQUAD",
                "turn": 0,
                "leftArm": {
                    "bend": -0.18953852355480194
                }
            },
            {
                "tick": 60,
                "easing": "EASEINOUTQUAD",
                "turn": 0,
                "leftArm": {
                    "bend": -0.18953852355480194
                }
            },
            {
                "tick": 1,
                "easing": "EASEINOUTQUAD",
                "turn": 0,
                "rightLeg": {
                    "yaw": 0.7265439629554749
                }
            },
            {
                "tick": 5,
                "easing": "EASEINOUTQUAD",
                "turn": 0,
                "rightLeg": {
                    "yaw": 0.7875269055366516
                }
            },
            {
                "tick": 40,
                "easing": "EASEINOUTQUAD",
                "turn": 0,
                "rightLeg": {
                    "yaw": 0.7265439629554749
                }
            },
            {
                "tick": 60,
                "easing": "EASEINOUTQUAD",
                "turn": 0,
                "rightLeg": {
                    "yaw": 0.7265439629554749
                }
            },
            {
                "tick": 1,
                "easing": "EASEINOUTQUAD",
                "turn": 0,
                "rightLeg": {
                    "roll": 0.6338891386985779
                }
            },
            {
                "tick": 5,
                "easing": "EASEINOUTQUAD",
                "turn": 0,
                "rightLeg": {
                    "roll": 0.396414190530777
                }
            },
            {
                "tick": 40,
                "easing": "EASEINOUTQUAD",
                "turn": 0,
                "rightLeg": {
                    "roll": 0.6338891386985779
                }
            },
            {
                "tick": 60,
                "easing": "EASEINOUTQUAD",
                "turn": 0,
                "rightLeg": {
                    "roll": 0.6338891386985779
                }
            },
            {
                "tick": 1,
                "easing": "EASEINOUTQUAD",
                "turn": 0,
                "rightLeg": {
                    "pitch": -0.3592376112937927
                }
            },
            {
                "tick": 5,
                "easing": "EASEINOUTQUAD",
                "turn": 0,
                "rightLeg": {
                    "pitch": -0.7030680179595947
                }
            },
            {
                "tick": 40,
                "easing": "EASEINOUTQUAD",
                "turn": 0,
                "rightLeg": {
                    "pitch": -0.3592376112937927
                }
            },
            {
                "tick": 60,
                "easing": "EASEINOUTQUAD",
                "turn": 0,
                "rightLeg": {
                    "pitch": -0.3592376112937927
                }
            },
            {
                "tick": 1,
                "easing": "EASEINOUTQUAD",
                "turn": 0,
                "rightLeg": {
                    "x": -1.8815152883529662
                }
            },
            {
                "tick": 5,
                "easing": "EASEINOUTQUAD",
                "turn": 0,
                "rightLeg": {
                    "x": -1.8815152883529662
                }
            },
            {
                "tick": 40,
                "easing": "EASEINOUTQUAD",
                "turn": 0,
                "rightLeg": {
                    "x": -1.9
                }
            },
            {
                "tick": 60,
                "easing": "EASEINOUTQUAD",
                "turn": 0,
                "rightLeg": {
                    "x": -1.9
                }
            },
            {
                "tick": 1,
                "easing": "EASEINOUTQUAD",
                "turn": 0,
                "rightLeg": {
                    "y": 11.935262098908424
                }
            },
            {
                "tick": 5,
                "easing": "EASEINOUTQUAD",
                "turn": 0,
                "rightLeg": {
                    "y": 11.935262098908424
                }
            },
            {
                "tick": 40,
                "easing": "EASEINOUTQUAD",
                "turn": 0,
                "rightLeg": {
                    "y": 12.0
                }
            },
            {
                "tick": 60,
                "easing": "EASEINOUTQUAD",
                "turn": 0,
                "rightLeg": {
                    "y": 12.0
                }
            },
            {
                "tick": 1,
                "easing": "EASEINOUTQUAD",
                "turn": 0,
                "rightLeg": {
                    "z": 0.10000000200644657
                }
            },
            {
                "tick": 5,
                "easing": "EASEINOUTQUAD",
                "turn": 0,
                "rightLeg": {
                    "z": 0.10000000200644657
                }
            },
            {
                "tick": 40,
                "easing": "EASEINOUTQUAD",
                "turn": 0,
                "rightLeg": {
                    "z": 0.1
                }
            },
            {
                "tick": 60,
                "easing": "EASEINOUTQUAD",
                "turn": 0,
                "rightLeg": {
                    "z": 0.1
                }
            },
            {
                "tick": 1,
                "easing": "EASEINOUTQUAD",
                "turn": 0,
                "rightLeg": {
                    "bend": 0.7973071932792664
                }
            },
            {
                "tick": 5,
                "easing": "EASEINOUTQUAD",
                "turn": 0,
                "rightLeg": {
                    "bend": 0.9642375111579895
                }
            },
            {
                "tick": 40,
                "easing": "EASEINOUTQUAD",
                "turn": 0,
                "rightLeg": {
                    "bend": 0.7908383011817932
                }
            },
            {
                "tick": 60,
                "easing": "EASEINOUTQUAD",
                "turn": 0,
                "rightLeg": {
                    "bend": 0.7908383011817932
                }
            },
            {
                "tick": 1,
                "easing": "EASEINOUTQUAD",
                "turn": 0,
                "leftLeg": {
                    "yaw": -0.2931945323944092
                }
            },
            {
                "tick": 5,
                "easing": "EASEINOUTQUAD",
                "turn": 0,
                "leftLeg": {
                    "yaw": -0.2958471477031708
                }
            },
            {
                "tick": 40,
                "easing": "EASEINOUTQUAD",
                "turn": 0,
                "leftLeg": {
                    "yaw": -0.2931945323944092
                }
            },
            {
                "tick": 60,
                "easing": "EASEINOUTQUAD",
                "turn": 0,
                "leftLeg": {
                    "yaw": -0.2931945323944092
                }
            },
            {
                "tick": 1,
                "easing": "EASEINOUTQUAD",
                "turn": 0,
                "leftLeg": {
                    "roll": 0.23800063133239746
                }
            },
            {
                "tick": 5,
                "easing": "EASEINOUTQUAD",
                "turn": 0,
                "leftLeg": {
                    "roll": 0.27689433097839355
                }
            },
            {
                "tick": 40,
                "easing": "EASEINOUTQUAD",
                "turn": 0,
                "leftLeg": {
                    "roll": 0.23800063133239746
                }
            },
            {
                "tick": 60,
                "easing": "EASEINOUTQUAD",
                "turn": 0,
                "leftLeg": {
                    "roll": 0.23800063133239746
                }
            },
            {
                "tick": 1,
                "easing": "EASEINOUTQUAD",
                "turn": 0,
                "leftLeg": {
                    "pitch": -0.8006985783576965
                }
            },
            {
                "tick": 5,
                "easing": "EASEINOUTQUAD",
                "turn": 0,
                "leftLeg": {
                    "pitch": -0.9345015287399292
                }
            },
            {
                "tick": 40,
                "easing": "EASEINOUTQUAD",
                "turn": 0,
                "leftLeg": {
                    "pitch": -0.8006985783576965
                }
            },
            {
                "tick": 60,
                "easing": "EASEINOUTQUAD",
                "turn": 0,
                "leftLeg": {
                    "pitch": -0.8006985783576965
                }
            },
            {
                "tick": 1,
                "easing": "EASEINOUTQUAD",
                "turn": 0,
                "leftLeg": {
                    "y": 13.068265438079834
                }
            },
            {
                "tick": 5,
                "easing": "EASEINOUTQUAD",
                "turn": 0,
                "leftLeg": {
                    "y": 13.068265438079834
                }
            },
            {
                "tick": 40,
                "easing": "EASEINOUTQUAD",
                "turn": 0,
                "leftLeg": {
                    "y": 13.133351683616638
                }
            },
            {
                "tick": 60,
                "easing": "EASEINOUTQUAD",
                "turn": 0,
                "leftLeg": {
                    "y": 13.133351683616638
                }
            },
            {
                "tick": 1,
                "easing": "EASEINOUTQUAD",
                "turn": 0,
                "leftLeg": {
                    "z": -0.10000003310915986
                }
            },
            {
                "tick": 5,
                "easing": "EASEINOUTQUAD",
                "turn": 0,
                "leftLeg": {
                    "z": -0.10000003310915986
                }
            },
            {
                "tick": 40,
                "easing": "EASEINOUTQUAD",
                "turn": 0,
                "leftLeg": {
                    "z": -0.1000000351264049
                }
            },
            {
                "tick": 60,
                "easing": "EASEINOUTQUAD",
                "turn": 0,
                "leftLeg": {
                    "z": -0.1000000351264049
                }
            },
            {
                "tick": 1,
                "easing": "EASEINOUTQUAD",
                "turn": 0,
                "leftLeg": {
                    "x": 1.594976806640625
                }
            },
            {
                "tick": 5,
                "easing": "EASEINOUTQUAD",
                "turn": 0,
                "leftLeg": {
                    "x": 1.594976806640625
                }
            },
            {
                "tick": 40,
                "easing": "EASEINOUTQUAD",
                "turn": 0,
                "leftLeg": {
                    "x": 1.5763926744461059
                }
            },
            {
                "tick": 60,
                "easing": "EASEINOUTQUAD",
                "turn": 0,
                "leftLeg": {
                    "x": 1.5763926744461059
                }
            },
            {
                "tick": 1,
                "easing": "EASEINOUTQUAD",
                "turn": 0,
                "leftLeg": {
                    "bend": 0.9514538049697876
                }
            },
            {
                "tick": 5,
                "easing": "EASEINOUTQUAD",
                "turn": 0,
                "leftLeg": {
                    "bend": 1.12519109249115
                }
            },
            {
                "tick": 40,
                "easing": "EASEINOUTQUAD",
                "turn": 0,
                "leftLeg": {
                    "bend": 0.9581573605537415
                }
            },
            {
                "tick": 60,
                "easing": "EASEINOUTQUAD",
                "turn": 0,
                "leftLeg": {
                    "bend": 0.9581573605537415
                }
            }
        ]
    }
}